README.md
setup.py
kindenty/__init__.py
kindenty/databaseConfig.py
kindenty/base/BaseDao.py
kindenty/base/BaseEnum.py
kindenty/base/BaseMethod.py
kindenty/base/BaseModel.py
kindenty/base/DatabaseDriver.py
kindenty/base/DatabasePool.py
kindenty/base/DatabaseType.py
kindenty/base/ExceptionModel.py
kindenty/base/OrmField.py
kindenty/base/QueueManager.py
kindenty/base/__init__.py
kindenty/dao/DatabaseDao.py
kindenty/dao/__init__.py
kindenty/model/DataDto.py
kindenty/model/DatabaseModel.py
kindenty/model/__init__.py
kindenty/mq/__init__.py
kindenty/mq/rabbitmq.py
kindenty_base.egg-info/PKG-INFO
kindenty_base.egg-info/SOURCES.txt
kindenty_base.egg-info/dependency_links.txt
kindenty_base.egg-info/top_level.txt