Metadata-Version: 2.1
Name: kindenty-base
Version: 0.1.26
Summary: 测试
Home-page: https://gitee.com/kindenty-yueyu/cats-strategy-core
Author: kindenty
Author-email: kindenty@163.com
License: UNKNOWN
Platform: UNKNOWN
Classifier: Programming Language :: Python :: 3
